dt_test/__init__.py
dt_test/cli.py
dt_test/dt_test.py
dt_test/data/miner.txt
dt_test-0.1.4.dist-info/METADATA
dt_test-0.1.4.dist-info/RECORD
dt_test-0.1.4.dist-info/WHEEL
dt_test-0.1.4.dist-info/entry_points.txt
dt_test-0.1.4.dist-info/top_level.txt
