Metadata-Version: 2.1
Name: dt-test
Version: 0.1.4
Summary: test pypi upload 
Home-page: https://github.com/kedpter/dt_test
Author: UNKNOWN
Author-email: 790476448@qq.com
License: MIT license
Keywords: dt_test
Platform: UNKNOWN
Classifier: Development Status :: 2 - Pre-Alpha
Classifier: Intended Audience :: Developers
Classifier: License :: OSI Approved :: MIT License
Classifier: Natural Language :: English
Classifier: Programming Language :: Python :: 2
Classifier: Programming Language :: Python :: 2.7
Classifier: Programming Language :: Python :: 3
Classifier: Programming Language :: Python :: 3.4
Classifier: Programming Language :: Python :: 3.5
Classifier: Programming Language :: Python :: 3.6
Requires-Dist: Click (>=6.0)
